snapshotter_cli/__init__.py
snapshotter_cli/__main__.py
snapshotter_cli/cli.py
snapshotter_cli/commands/__init__.py
snapshotter_cli/commands/configure.py
snapshotter_cli/commands/deploy.py
snapshotter_cli/commands/diagnose.py
snapshotter_cli/commands/identity.py
snapshotter_cli/commands/shell.py
snapshotter_cli/commands/status.py
snapshotter_cli/utils/__init__.py
snapshotter_cli/utils/changelog.py
snapshotter_cli/utils/config_helpers.py
snapshotter_cli/utils/console.py
snapshotter_cli/utils/deployment.py
snapshotter_cli/utils/docker_utils.py
snapshotter_cli/utils/env.py
snapshotter_cli/utils/evm.py
snapshotter_cli/utils/models.py
snapshotter_cli/utils/settings_models.py
snapshotter_cli/utils/system_checks.py
snapshotter_cli/utils/abi/PowerloomNodes.json
snapshotter_cli/utils/abi/ProtocolState.json
snapshotter_cli/CHANGELOG.md
powerloom_snapshotter_cli-0.1.6.dist-info/METADATA
powerloom_snapshotter_cli-0.1.6.dist-info/WHEEL
powerloom_snapshotter_cli-0.1.6.dist-info/entry_points.txt
powerloom_snapshotter_cli-0.1.6.dist-info/licenses/LICENSE
powerloom_snapshotter_cli-0.1.6.dist-info/RECORD
