Metadata-Version: 2.4
Name: powerloom-snapshotter-cli
Version: 0.1.6
Summary: CLI tool for deploying and managing Powerloom Snapshotter nodes
Project-URL: Bug Tracker, https://github.com/powerloom/snapshotter-lite-multi-setup/issues
Project-URL: Changelog, https://github.com/powerloom/snapshotter-lite-multi-setup/blob/master/CHANGELOG.md
Project-URL: Twitter, https://x.com/powerloom
Author-email: Powerloom Protocol <hello@powerloom.io>
License: MIT
License-File: LICENSE
Keywords: blockchain,cli,ethereum,node-management,powerloom,snapshotter,web3
Classifier: Development Status :: 4 - Beta
Classifier: Environment :: Console
Classifier: Intended Audience :: Developers
Classifier: Intended Audience :: System Administrators
Classifier: License :: OSI Approved :: MIT License
Classifier: Operating System :: MacOS :: MacOS X
Classifier: Operating System :: POSIX :: Linux
Classifier: Programming Language :: Python :: 3
Classifier: Programming Language :: Python :: 3.12
Classifier: Programming Language :: Python :: 3.13
Classifier: Topic :: Software Development :: Libraries :: Python Modules
Classifier: Topic :: System :: Systems Administration
Classifier: Topic :: Utilities
Requires-Python: <3.14,>=3.12
Requires-Dist: psutil>=5.9.8
Requires-Dist: pydantic>=2.10.4
Requires-Dist: python-dotenv>=1.0.1
Requires-Dist: rich>=13.7.0
Requires-Dist: toml>=0.10.2
Requires-Dist: typer[all]==0.15.4
Requires-Dist: web3>=6.15.1
